citation_hallucination_stop/__init__.py
citation_hallucination_stop/cleaner.py
citation_hallucination_stop/utils.py
citation_hallucination_stop-1.0.1.dist-info/licenses/LICENSE
citation_hallucination_stop-1.0.1.dist-info/METADATA
citation_hallucination_stop-1.0.1.dist-info/WHEEL
citation_hallucination_stop-1.0.1.dist-info/entry_points.txt
citation_hallucination_stop-1.0.1.dist-info/top_level.txt
citation_hallucination_stop-1.0.1.dist-info/RECORD
